{
  "checkInterval": 10000,
  "dedicatedCheckInterval": 1000,
  "pve": {
    "maxRoomPoolSizePerZone": 5000,
    "minRoomPoolSizePerZone": 10,
    "maxDedicatedServerConnections": 10
  },
  "pvp": {
    "maxRoomPoolSizePerZone": 100,
    "minRoomPoolSizePerZone": 10,
    "maxDedicatedServerConnections": 10
  },
  "tve": {
    "maxRoomPoolSizePerZone": 2000,
    "minRoomPoolSizePerZone": 100,
    "maxDedicatedServerConnections": 10
  },
  "tvt": {
    "maxRoomPoolSizePerZone": 2000,
    "minRoomPoolSizePerZone": 100,
    "maxDedicatedServerConnections": 10
  }
}